openssa/Makefile
openssa/README.md
openssa/VERSION
openssa/__init__.py
openssa/contrib/README.md
openssa/contrib/__init__.py
openssa/contrib/streamlit_ssa_prob_solver.py
openssa/core/__init__.py
openssa/core/adapter/__init__.py
openssa/core/adapter/abstract_adapter.py
openssa/core/adapter/base_adapter.py
openssa/core/backend/__init__.py
openssa/core/backend/abstract_backend.py
openssa/core/backend/base_backend.py
openssa/core/backend/rag_backend.py
openssa/core/backend/text_backend.py
openssa/core/inferencer/__init__.py
openssa/core/inferencer/abstract_inferencer.py
openssa/core/inferencer/base_inferencer.py
openssa/core/ooda_rag/heuristic.py
openssa/core/ooda_rag/notifier.py
openssa/core/ooda_rag/ooda_rag.py
openssa/core/ooda_rag/prompts.py
openssa/core/ooda_rag/tools.py
openssa/core/prompts.py
openssa/core/slm/__init__.py
openssa/core/slm/abstract_slm.py
openssa/core/slm/base_slm.py
openssa/core/slm/memory/__init__.py
openssa/core/slm/memory/conversation_db.py
openssa/core/slm/memory/sqlite_conversation_db.py
openssa/core/ssa/__init__.py
openssa/core/ssa/rag_ssa.py
openssa/core/ssa/ssa.py
openssa/core/ssa/ssa_service.py
openssa/core/ssm/__init__.py
openssa/core/ssm/abstract_ssm.py
openssa/core/ssm/abstract_ssm_builder.py
openssa/core/ssm/base_ssm.py
openssa/core/ssm/base_ssm_builder.py
openssa/core/ssm/rag_ssm.py
openssa/industrial/interpretability/README.md
openssa/industrial/monitoring/README.md
openssa/industrial/security/README.md
openssa/industrial/security/audit/README.md
openssa/industrial/security/best_practices/README.md
openssa/integrations/README.md
openssa/integrations/__init__.py
openssa/integrations/api_context.py
openssa/integrations/azure/ssm.py
openssa/integrations/huggingface/__init__.py
openssa/integrations/huggingface/slm.py
openssa/integrations/huggingface/ssm.py
openssa/integrations/lepton_ai/__init__.py
openssa/integrations/lepton_ai/ssm.py
openssa/integrations/llama_index/README.md
openssa/integrations/llama_index/__init__.py
openssa_dev-0.1.6.5.dist-info/LICENSE.md
openssa_dev-0.1.6.5.dist-info/METADATA
openssa_dev-0.1.6.5.dist-info/WHEEL
openssa_dev-0.1.6.5.dist-info/RECORD
