Metadata-Version: 2.1
Name: openssa-dev
Version: 0.1.6.5
Summary: OpenSSA - 'Small Specialist Agents' for Industrial AI
Author: Aitomatic Engineering
Author-email: engineering@aitomatic.com
Requires-Python: >=3.10,<3.12
Classifier: Programming Language :: Python :: 3
Classifier: Programming Language :: Python :: 3.10
Classifier: Programming Language :: Python :: 3.11
Provides-Extra: cv
Requires-Dist: adlfs (>=2023.10.0)
Requires-Dist: docx2txt (>=0.8)
Requires-Dist: fsspec (>=2023.10.0)
Requires-Dist: gcsfs (>=2023.10.0)
Requires-Dist: gdrivefs (>=0.14.13)
Requires-Dist: google-api-python-client (>=2.108.0)
Requires-Dist: httpx (>=0.25.2)
Requires-Dist: llama-hub (>=0.0.48)
Requires-Dist: llama-index (>=0.9.8,<0.10.0)
Requires-Dist: nltk (>=3.8.1)
Requires-Dist: openai (>=1.3.2,<1.4.0)
Requires-Dist: pillow (>=9.5) ; extra == "cv"
Requires-Dist: pycryptodome (>=3.19.0)
Requires-Dist: pydantic (>=2.5.2)
Requires-Dist: pydocstyle (>=6.3.0)
Requires-Dist: pypdf (>=3.17.1)
Requires-Dist: pytest (>=7.4.3)
Requires-Dist: python-dotenv (>=1.0.0)
Requires-Dist: python-pptx (>=0.6.23) ; extra == "cv"
Requires-Dist: s3fs (>=2023.10.0)
Requires-Dist: torch (>=2.0) ; extra == "cv"
Requires-Dist: transformers (>=4.35.2) ; extra == "cv"
